external_proc/__init__.py
external_proc/_external_proc.cp36-win_amd64.pyd
external_proc/_external_proc.pyi
external_proc/external_proc.py
external_proc/get_proc_x32.exe
external_proc/get_proc_x64.exe
external_proc-0.0.2.dist-info/METADATA
external_proc-0.0.2.dist-info/WHEEL
external_proc-0.0.2.dist-info/top_level.txt
external_proc-0.0.2.dist-info/RECORD
