Metadata-Version: 2.1
Name: external-proc
Version: 0.0.2
Summary: pybind11 extension
Home-page: UNKNOWN
Author: bananasss00
Author-email: bananasss00@yandex.com
License: UNKNOWN
Platform: UNKNOWN
Classifier: Operating System :: Microsoft :: Windows :: Windows 10
Classifier: Programming Language :: Python :: 3.6
Classifier: Programming Language :: Python :: 3.7
Classifier: Programming Language :: Python :: 3.8
Classifier: Programming Language :: Python :: 3.9
Requires: pybind11
Requires-Python: >=3.6,<4.0
